mysql_mcp_server/__init__.py
mysql_mcp_server/server.py
nm_mysql_mcp_server-0.1.0.dist-info/METADATA
nm_mysql_mcp_server-0.1.0.dist-info/WHEEL
nm_mysql_mcp_server-0.1.0.dist-info/entry_points.txt
nm_mysql_mcp_server-0.1.0.dist-info/top_level.txt
nm_mysql_mcp_server-0.1.0.dist-info/RECORD
