Metadata-Version: 2.4
Name: nm-mysql-mcp-server
Version: 0.1.0
Summary: Add your description here
Requires-Python: >=3.13
Requires-Dist: mcp>=1.0.0
Requires-Dist: mysql-connector-python>=9.1.0
